setup.py
autoself/__init__.py
autoself/testmeta.py
autoself.egg-info/PKG-INFO
autoself.egg-info/SOURCES.txt
autoself.egg-info/dependency_links.txt
autoself.egg-info/top_level.txt
