Metadata-Version: 1.0
Name: autoself
Version: 1.0.0
Summary: Automagically add 'self' argument to method definitions
Home-page: http://www.rfk.id.au/software/autoself/
Author: Ryan Kelly
Author-email: ryan@rfk.id.au
License: Public Domain
Keywords: self method
Platform: UNKNOWN
